gffx/__init__.py
gffx/__main__.py
gffx/context/__init__.py
gffx/io/__init__.py
gffx/io/__main__.py
gffx/linalg/__init__.py
gffx/obj/__init__.py
gffx/ray/__init__.py
gffx/ray/camera.py
gffx/utils.py
gffx-0.1.4.dist-info/LICENSE
gffx-0.1.4.dist-info/METADATA
gffx-0.1.4.dist-info/WHEEL
gffx-0.1.4.dist-info/RECORD
