Metadata-Version: 2.3
Name: gffx
Version: 0.1.4
Summary: A minimal graphics library in PyTorch
License: MIT
Author: Danzel Serrano
Author-email: danzel.serrano@gmail.com
Requires-Python: >=3.8,<4.0
Classifier: License :: OSI Approved :: MIT License
Classifier: Programming Language :: Python :: 3
Classifier: Programming Language :: Python :: 3.8
Classifier: Programming Language :: Python :: 3.9
Classifier: Programming Language :: Python :: 3.10
Classifier: Programming Language :: Python :: 3.11
Classifier: Programming Language :: Python :: 3.12
Classifier: Programming Language :: Python :: 3.13
Project-URL: Repository, https://github.com/dependanz/gffx
